Metadata-Version: 2.1
Name: NumericalMethodsLib
Version: 0.0.1
Summary: Numerical method functions
Home-page: UNKNOWN
Author: Terry Slevin
Author-email: TerrenceSlevin1999@gmail.com
License: MIT
Keywords: numerical methods
Platform: UNKNOWN
Classifier: Development Status :: 5 - Production/Stable
Classifier: Intended Audience :: Science/Research
Classifier: Operating System :: Microsoft :: Windows :: Windows 11
Classifier: License :: OSI Approved :: MIT License
Classifier: Programming Language :: Python :: 3
License-File: LICENSE.txt
